decocli/__init__.py
decocli/cli.py
decocli/cmd.py
decocli/param.py
decocli/parser.py
decocli-0.3.dist-info/LICENSE
decocli-0.3.dist-info/METADATA
decocli-0.3.dist-info/WHEEL
decocli-0.3.dist-info/top_level.txt
decocli-0.3.dist-info/RECORD
